django_rest_crypto/__init__.py
django_rest_crypto/encrypt.py
django_rest_crypto/middlewares.py
django_rest_crypto/version.json
django_rest_crypto-1.0.2.dist-info/METADATA
django_rest_crypto-1.0.2.dist-info/WHEEL
django_rest_crypto-1.0.2.dist-info/top_level.txt
django_rest_crypto-1.0.2.dist-info/RECORD
