Metadata-Version: 2.1
Name: django-rest-crypto
Version: 1.0.2
Summary: Crypto Middleware for DjangoRestFramework
Home-page: https://github.com/suqingdong/django_rest_crypto
Author: suqingdong
Author-email: suqingdong1114@gmail.com
License: BSD License
Project-URL: Documentation, https://django_rest_crypto.readthedocs.io
Project-URL: Tracker, https://github.com/suqingdong/django_rest_crypto/issues
Platform: UNKNOWN
Classifier: Development Status :: 5 - Production/Stable
Classifier: Operating System :: OS Independent
Classifier: Intended Audience :: Developers
Classifier: License :: OSI Approved :: MIT License
Classifier: Programming Language :: Python
Classifier: Programming Language :: Python :: 3
Classifier: Programming Language :: Python :: 3.8
Classifier: Topic :: Software Development :: Libraries
Requires-Dist: django
Requires-Dist: pycryptodomex
